kisters/network_store/model_library/base/__init__.py
kisters/network_store/model_library/base/base.py
kisters/network_store/model_library/base/py.typed
kisters/network_store/model_library/util/__init__.py
kisters/network_store/model_library/util/py.typed
kisters/network_store/model_library/util/util.py
kisters_network_store_model_library-0.6.4.dist-info/METADATA
kisters_network_store_model_library-0.6.4.dist-info/WHEEL
kisters_network_store_model_library-0.6.4.dist-info/top_level.txt
kisters_network_store_model_library-0.6.4.dist-info/RECORD
