Metadata-Version: 2.4
Name: kisters.network_store.model_library
Version: 0.6.4
Summary: Model Library Base for the Kisters Network Store
Author-email: Jesse VanderWees <jesse.vanderwees@kisters-bv.nl>
Project-URL: Homepage, https://gitlab.com/kisters/network-store/model-library-water
Classifier: Development Status :: 3 - Alpha
Classifier: Intended Audience :: Developers
Classifier: Programming Language :: Python :: 3
Classifier: License :: OSI Approved :: GNU Lesser General Public License v2 or later (LGPLv2+)
Classifier: Operating System :: OS Independent
Requires-Python: >=3.9
Requires-Dist: pydantic>=2
Provides-Extra: test
Requires-Dist: pytest; extra == "test"
Provides-Extra: mypy
Requires-Dist: kisters.network_store.model_library[test]; extra == "mypy"
Requires-Dist: mypy; extra == "mypy"
